Metadata-Version: 2.1
Name: hxz-pandora-cloud
Version: 1.0.4
Summary: A package for hxz_pandora-ChatGPT
Home-page: https://github.com/shoot82003/hxz_pandora_cloud
Author: Xiaozhou Huang
Author-email: shoot82003@qq.com
Project-URL: Source, https://github.com/shoot82003/hxz_pandora_cloud
Project-URL: Tracker, https://github.com/shoot82003/hxz_pandora_cloud/issues
Keywords: OpenAI ChatGPT ChatGPT-Plus
Classifier: Development Status :: 4 - Beta
Classifier: Environment :: Web Environment
Classifier: Framework :: Flask
Classifier: Intended Audience :: Developers
Classifier: Intended Audience :: End Users/Desktop
Classifier: License :: OSI Approved :: GNU General Public License v2 (GPLv2)
Classifier: Natural Language :: English
Classifier: Natural Language :: Chinese (Simplified)
Classifier: Operating System :: MacOS
Classifier: Operating System :: Microsoft :: Windows
Classifier: Operating System :: POSIX :: Linux
Classifier: Programming Language :: JavaScript
Classifier: Programming Language :: Python :: 3.7
Classifier: Programming Language :: Python :: 3.8
Classifier: Programming Language :: Python :: 3.9
Classifier: Programming Language :: Python :: 3.10
Classifier: Programming Language :: Python :: 3.11
Classifier: Topic :: Communications :: Chat
Classifier: Topic :: Internet :: WWW/HTTP
Requires-Python: >=3.7
License-File: LICENSE
